openlanev2/__init__.py
openlanev2/utils.py
openlanev2/centerline/__init__.py
openlanev2/centerline/dataset/__init__.py
openlanev2/centerline/dataset/collection.py
openlanev2/centerline/dataset/frame.py
openlanev2/centerline/evaluation/__init__.py
openlanev2/centerline/evaluation/distance.py
openlanev2/centerline/evaluation/evaluate.py
openlanev2/centerline/evaluation/f_score.py
openlanev2/centerline/io/__init__.py
openlanev2/centerline/io/io.py
openlanev2/centerline/preprocessing/__init__.py
openlanev2/centerline/preprocessing/check.py
openlanev2/centerline/preprocessing/collect.py
openlanev2/centerline/visualization/__init__.py
openlanev2/centerline/visualization/bev.py
openlanev2/centerline/visualization/pv.py
openlanev2/centerline/visualization/sdmap.py
openlanev2/centerline/visualization/utils.py
openlanev2/lanesegment/__init__.py
openlanev2/lanesegment/dataset/__init__.py
openlanev2/lanesegment/dataset/collection.py
openlanev2/lanesegment/dataset/frame.py
openlanev2/lanesegment/evaluation/__init__.py
openlanev2/lanesegment/evaluation/distance.py
openlanev2/lanesegment/evaluation/evaluate.py
openlanev2/lanesegment/io/__init__.py
openlanev2/lanesegment/preprocessing/__init__.py
openlanev2/lanesegment/preprocessing/collect.py
openlanev2/lanesegment/visualization/__init__.py
openlanev2/lanesegment/visualization/bev.py
openlanev2/lanesegment/visualization/pv.py
openlanev2/lanesegment/visualization/sdmap.py
openlanev2/lanesegment/visualization/utils.py
openlanev2-2.1.0.dist-info/LICENSE
openlanev2-2.1.0.dist-info/METADATA
openlanev2-2.1.0.dist-info/WHEEL
openlanev2-2.1.0.dist-info/top_level.txt
openlanev2-2.1.0.dist-info/RECORD
