Metadata-Version: 2.1
Name: openlanev2
Version: 2.1.0
Summary: The official devkit of the OpenLane-V2 dataset.
Home-page: https://github.com/OpenDriveLab/OpenLane-V2
Author: The OpenLane-V2 Dataset Authors
Author-email: wanghuijie@pjlab.org.cn
License: Apache License 2.0
License-File: LICENSE
Requires-Dist: tqdm
Requires-Dist: ninja
Requires-Dist: jupyter
Requires-Dist: openmim
Requires-Dist: matplotlib
Requires-Dist: numpy <1.24.0,>=1.22.0
Requires-Dist: scikit-learn
Requires-Dist: similaritymeasures
Requires-Dist: opencv-python
Requires-Dist: scipy ==1.8.0
Requires-Dist: ortools ==9.2.9972
Requires-Dist: iso3166
Requires-Dist: chardet
Requires-Dist: shapely ==2.0.0
